decorator.cp312-win_amd64.pyd
error.cp312-win_amd64.pyd
exception.cp312-win_amd64.pyd
globals.cp312-win_amd64.pyd
parser.cp312-win_amd64.pyd
type.cp312-win_amd64.pyd
guerrilla/__init__.c
guerrilla/__init__.cp312-win_amd64.pyd
guerrilla/__init__.py
guerrilla/connection/__init__.c
guerrilla/connection/__init__.cp312-win_amd64.pyd
guerrilla/connection/__init__.py
guerrilla/connection/channel.c
guerrilla/connection/channel.cp312-win_amd64.pyd
guerrilla/connection/channel.py
guerrilla/connection/response.c
guerrilla/connection/response.cp312-win_amd64.pyd
guerrilla/connection/response.py
guerrilla/connection/session.c
guerrilla/connection/session.cp312-win_amd64.pyd
guerrilla/connection/session.py
guerrilla/connection/ssh.c
guerrilla/connection/ssh.cp312-win_amd64.pyd
guerrilla/connection/ssh.py
guerrilla/device/__init__.c
guerrilla/device/__init__.cp312-win_amd64.pyd
guerrilla/device/__init__.py
guerrilla/device/base.c
guerrilla/device/base.cp312-win_amd64.pyd
guerrilla/device/base.py
guerrilla/device/linux/__init__.c
guerrilla/device/linux/__init__.cp312-win_amd64.pyd
guerrilla/device/linux/__init__.py
guerrilla/device/linux/command.c
guerrilla/device/linux/command.cp312-win_amd64.pyd
guerrilla/device/linux/command.py
guerrilla/device/linux/linux.c
guerrilla/device/linux/linux.cp312-win_amd64.pyd
guerrilla/device/linux/linux.py
guerrilla/device/router/__init__.c
guerrilla/device/router/__init__.cp312-win_amd64.pyd
guerrilla/device/router/__init__.py
guerrilla/device/router/command.c
guerrilla/device/router/command.cp312-win_amd64.pyd
guerrilla/device/router/command.py
guerrilla/device/router/mode.c
guerrilla/device/router/mode.cp312-win_amd64.pyd
guerrilla/device/router/mode.py
guerrilla/device/router/router.c
guerrilla/device/router/router.cp312-win_amd64.pyd
guerrilla/device/router/router.py
guerrilla/device/router/config/__init__.c
guerrilla/device/router/config/__init__.cp312-win_amd64.pyd
guerrilla/device/router/config/__init__.py
guerrilla-0.2.1.dist-info/METADATA
guerrilla-0.2.1.dist-info/WHEEL
guerrilla-0.2.1.dist-info/top_level.txt
guerrilla-0.2.1.dist-info/RECORD
