Metadata-Version: 2.1
Name: guerrilla
Version: 0.2.1
Summary: Moxa Router Automation Testing Framework
Author-email: "kaneja.lin.moxa" <KaneJA_Lin@moxa.com>
License: MIT
Requires-Python: >=3.12
Requires-Dist: scapy >=2.5.0
Requires-Dist: pexpect >=4.8.0
Requires-Dist: pyserial >=3.5
Requires-Dist: textfsm >=1.1.3
Requires-Dist: python-box >=7.1.1
Requires-Dist: paramiko >=3.3.1
Requires-Dist: loguru >=0.7.2
Requires-Dist: yaspin >=3.0.1
